hivemind_sqlite_database/__init__.py
hivemind_sqlite_database/version.py
hivemind_sqlite_database-0.0.3.dist-info/LICENSE.md
hivemind_sqlite_database-0.0.3.dist-info/METADATA
hivemind_sqlite_database-0.0.3.dist-info/WHEEL
hivemind_sqlite_database-0.0.3.dist-info/entry_points.txt
hivemind_sqlite_database-0.0.3.dist-info/top_level.txt
hivemind_sqlite_database-0.0.3.dist-info/RECORD
