Metadata-Version: 2.1
Name: hivemind-sqlite-database
Version: 0.0.3
Summary: sqlite database plugin for hivemind-core
Home-page: https://github.com/JarbasHiveMind/hivemind-sqlite-database
Author: jarbasAi
Author-email: jarbasai@mailfence.com
License: Apache-2.0
Platform: UNKNOWN
Requires-Dist: hivemind-plugin-manager<1.0.0,>=0.1.0
